snowyowl/Snowflake.py
snowyowl/__init__.py
snowyowl/get_data.py
snowyowl/put_data.py
snowyowl/run_query.py
snowyowl-2020.11.12.dist-info/METADATA
snowyowl-2020.11.12.dist-info/WHEEL
snowyowl-2020.11.12.dist-info/top_level.txt
snowyowl-2020.11.12.dist-info/zip-safe
snowyowl-2020.11.12.dist-info/RECORD
