Metadata-Version: 2.1
Name: snowyowl
Version: 2020.11.12
Summary: Python library for working with Snowflake data warehouse
Home-page: https://github.com/idin/snowyowl
Author: Idin
Author-email: py@idin.ca
License: MIT
Keywords: database
Platform: UNKNOWN
Classifier: Development Status :: 3 - Alpha
Classifier: Intended Audience :: Developers
Classifier: License :: OSI Approved :: MIT License
Classifier: Programming Language :: Python :: 3 :: Only
Classifier: Programming Language :: Python :: 3.6
Classifier: Programming Language :: Python :: 3.7
Classifier: Topic :: Software Development :: Libraries :: Python Modules
Requires-Python: ~=3.6
Requires-Dist: snowflake-connector-python
Requires-Dist: sqlalchemy
Requires-Dist: pandas
